{
    "subject": "Logic",
    "topic": "Binary Operations",
    "subtopic": "Introduction",
    "views" : "1245",
    "datePublished": "May 28, 2024",
    "dateUpdated" : "May 28, 2024",
    "title" : "The 16 Binary Logic Operations",
    "description" : "Binary logic gates are the building blocks of digital circuits. They are used to perform binary operations on binary numbers. There are 16 possible binary logic operations. This lesson introduces the 16 binary logic operations and explains the meaning of a binary operation.",
    "objectives" : [
        "Understand the meaning of a binary operation",
        "Understand the meaning of a binary logic operation",
        "Recognize the 16 binary logic operations",
        "Understand the meaning of a commutative binary logic operation"
    ],
    "prerequisites" : [
        "Love of mathematics"
    ]
}